ecapybara/__init__.py
ecapybara/ecapydriver.py
ecapybara/ecapyworld.py
ecapybara-0.0.3.dist-info/METADATA
ecapybara-0.0.3.dist-info/WHEEL
ecapybara-0.0.3.dist-info/licenses/LICENSE
ecapybara-0.0.3.dist-info/RECORD
