Metadata-Version: 2.3
Name: ecapybara
Version: 0.0.3
Summary: Elementary Computational Automata for PYthon
Project-URL: Homepage, https://github.com/nrejack/ecapybara
Project-URL: Issues, https://github.com/nrejack/ecapybara/issues
Author-email: Nicholas Rejack <nrejack@users.noreply.github.com>
License-File: LICENSE
Classifier: Development Status :: 3 - Alpha
Classifier: License :: OSI Approved :: GNU General Public License v3 (GPLv3)
Classifier: Operating System :: OS Independent
Classifier: Programming Language :: Python :: 3
Classifier: Topic :: Artistic Software
Requires-Python: >=3.8
